bbml/__init__.py
bbml/ensemble.py
bbml-0.0.1.dist-info/LICENSE
bbml-0.0.1.dist-info/METADATA
bbml-0.0.1.dist-info/WHEEL
bbml-0.0.1.dist-info/top_level.txt
bbml-0.0.1.dist-info/RECORD
