Metadata-Version: 2.1
Name: bbml
Version: 0.0.1
Summary: For fitting classification with customized cost matrix
Home-page: 
Author: Bijan B
Author-email: tapesh.2022b@gmail.com
Classifier: Programming Language :: Python :: 3
Classifier: License :: OSI Approved :: MIT License
Classifier: Operating System :: OS Independent
Requires-Python: >=3.7
License-File: LICENSE
